[
  {
    "title": "محاسب",
    "link": "https://www.wadhefa.com/details/job/89032/",
    "company": "جدة",
    "time": "04/03/2026"
  },
  {
    "title": "الخدمات الطبية للقوات المسلحة تعلن وظائف شاغرة عبر جدارات بالرياض والظهران",
    "link": "https://www.ewdifh.com/jobs/84622",
    "company": "الخدمات الصحية بوزارة الدفاع",
    "time": "منذ 3 أيام"
  },
  {
    "title": "وزارة الطاقة تعلن وظيفة شاغرة بمسمى سائق لحملة الثانوية العامة بالرياض",
    "link": "https://www.ewdifh.com/jobs/84633",
    "company": "وزارة الطاقة",
    "time": "منذ يوم"
  },
  {
    "title": "أكاديمية الطاقة والمياه تعلن برنامج تدريب مبتدئ بالتوظيف بالمنطقة الغربية",
    "link": "https://www.ewdifh.com/jobs/84626",
    "company": "أكاديمية الطاقة والمياه",
    "time": "منذ يومين"
  },
  {
    "title": "جامعة الأمير سطام تعلن طرح وظائف أكاديمية شاغرة عن طريق نقل الخدمات",
    "link": "https://www.wadhefa.com/news/20281/",
    "company": "اعلان توظيف",
    "time": "03/03/2026"
  },
  {
    "title": "المدينة الطبية بجامعة القصيم تعلن فرص تدريبية عبر برنامج (تمهير)",
    "link": "https://www.ewdifh.com/jobs/84635",
    "company": "جامعة القصيم",
    "time": "منذ يوم"
  },
  {
    "title": "معهد ريادة يعلن دورة مجانية (عن بُعد) بمجال حقوق الملكية الفكرية",
    "link": "https://www.ewdifh.com/jobs/84624",
    "company": "معهد ريادة الأعمال الوطني",
    "time": "منذ يومين"
  },
  {
    "title": "موظف استقبال تأجير سيارات",
    "link": "https://www.wadhefa.com/details/job/88941/",
    "company": "الرياض - منطقة الرياض",
    "time": "اليوم"
  },
  {
    "title": "شركة ضيوف البيت تعلن وظائف موسمية لموسم حج 1447هـ في عدة تخصصات",
    "link": "https://www.ewdifh.com/jobs/84630",
    "company": "شركة ضيوف البيت",
    "time": "منذ يوم"
  },
  {
    "title": "امين متجر الكتروني",
    "link": "https://www.wadhefa.com/details/job/89026/",
    "company": "الرياض",
    "time": "03/03/2026"
  },
  {
    "title": "اخصائي مبيعات",
    "link": "https://www.wadhefa.com/details/job/89027/",
    "company": "مدن متفرقة",
    "time": "03/03/2026"
  },
  {
    "title": "مكتبة الملك فهد العامة بجدة تعلن 8 دورات تدريبية (عن بُعد) بمختلف المجالات",
    "link": "https://www.ewdifh.com/jobs/84621",
    "company": "مكتبة الملك فهد العامة بجدة",
    "time": "منذ 4 أيام"
  },
  {
    "title": "المركز الوطني لنظم الموارد الحكومية يعلن وظائف للجنسين عبر جدارات بالرياض",
    "link": "https://www.ewdifh.com/jobs/84632",
    "company": "المركز الوطني لنظم الموارد الحكومية",
    "time": "منذ يوم"
  },
  {
    "title": "كاتب تأجير سيارات",
    "link": "https://www.wadhefa.com/details/job/88914/",
    "company": "جدة - منطقة مكة",
    "time": "اليوم"
  },
  {
    "title": "مصرف الإنماء يعلن وظيفة ممثل مصرفية شخصية لحديثي التخرج بالرياض",
    "link": "https://www.ewdifh.com/jobs/84617",
    "company": "مصرف الإنماء",
    "time": "منذ 5 أيام"
  },
  {
    "title": "مستشفى الملك فيصل التخصصي يعلن 12 وظيفة للدبلوم فأعلى في 3 مدن",
    "link": "https://www.wadhefa.com/news/20283/",
    "company": "موقع المستشفى",
    "time": "03/03/2026"
  },
  {
    "title": "جامعة حائل تعلن فتح باب القبول في برامج الماجستير المجانية والمدفوعة 1448هـ",
    "link": "https://www.ewdifh.com/jobs/84628",
    "company": "جامعة حائل",
    "time": "منذ يومين"
  },
  {
    "title": "موظف خدمة عملاء",
    "link": "https://www.wadhefa.com/details/job/88781/",
    "company": "شقراء - منطقة الرياض",
    "time": "اليوم"
  },
  {
    "title": "محاسب",
    "link": "https://www.wadhefa.com/details/job/89029/",
    "company": "الرياض",
    "time": "03/03/2026"
  },
  {
    "title": "كاتب تأجير سيارات",
    "link": "https://www.wadhefa.com/details/job/88866/",
    "company": "الرياض - منطقة الرياض",
    "time": "اليوم"
  },
  {
    "title": "مندوب مشتريات",
    "link": "https://www.wadhefa.com/details/job/89031/",
    "company": "الدمام",
    "time": "04/03/2026"
  },
  {
    "title": "ممثل مبيعات",
    "link": "https://www.wadhefa.com/details/job/88895/",
    "company": "الرياض - منطقة الرياض",
    "time": "اليوم"
  },
  {
    "title": "شركة آيوا تعلن وظائف شاغرة لحملة الثانوية فأعلى في مدن المنطقة الشرقية",
    "link": "https://www.ewdifh.com/jobs/84638",
    "company": "متاجر ايوا (Eyewa)",
    "time": "منذ 22 ساعة"
  },
  {
    "title": "جامعة حائل تعلن توفر 11 وظيفة تعاقدية شاغرة عبر منصة (جدارات)",
    "link": "https://www.ewdifh.com/jobs/84639",
    "company": "جامعة حائل",
    "time": "منذ 15 ساعة"
  },
  {
    "title": "جامعة الملك عبدالله كاوست تعلن 11 وظيفة شاغرة لحملة البكالوريوس فأعلى",
    "link": "https://www.wadhefa.com/news/20284/",
    "company": "اعلان توظيف",
    "time": "03/03/2026"
  },
  {
    "title": "مركز وقاء يعلن بدء التقديم في برنامج التدريب التعاوني 2026م للجنسين",
    "link": "https://www.ewdifh.com/jobs/84625",
    "company": "مركز وقاء",
    "time": "منذ يومين"
  },
  {
    "title": "الأكاديمية المالية تعلن إطلاق برنامج تطوير الخريجين المجاني للرجال والنساء",
    "link": "https://www.wadhefa.com/news/20285/",
    "company": "اعلان تدريب",
    "time": "03/03/2026"
  },
  {
    "title": "جامعة الإمام تعلن وظائف عن طريق نقل الخدمات لمن هم على سلم الموظفين العام",
    "link": "https://www.ewdifh.com/jobs/84616",
    "company": "جامعة الإمام محمد بن سعود",
    "time": "منذ 5 أيام"
  },
  {
    "title": "شركة ينبع أرامكو سينوبك ياسرف تعلن طرح وظائف تقنية شاغرة للبكالوريوس",
    "link": "https://www.wadhefa.com/news/20282/",
    "company": "موقع الشركة",
    "time": "03/03/2026"
  },
  {
    "title": "شركة الصحة القابضة تعلن 3150 وظيفة صحية في كافة مناطق المملكة",
    "link": "https://www.ewdifh.com/jobs/84620",
    "company": "شركة الصحة القابضة",
    "time": "منذ 5 أيام"
  },
  {
    "title": "مهندس جودة",
    "link": "https://www.wadhefa.com/details/job/88897/",
    "company": "الرياض - منطقة الرياض",
    "time": "اليوم"
  },
  {
    "title": "بائع",
    "link": "https://www.wadhefa.com/details/job/89030/",
    "company": "الرياض",
    "time": "04/03/2026"
  },
  {
    "title": "مسئولة تحصيل",
    "link": "https://www.wadhefa.com/details/job/88783/",
    "company": "الرياض - منطقة الرياض",
    "time": "اليوم"
  },
  {
    "title": "شركة الأهلي المالية تعلن بدء التقديم في برنامج وجهتك المهنية لتأهيل الخريجين",
    "link": "https://www.ewdifh.com/jobs/84623",
    "company": "الأهلي كابيتال",
    "time": "منذ 3 أيام"
  },
  {
    "title": "Customer services executive",
    "link": "https://www.wadhefa.com/details/job/89028/",
    "company": "الرياض",
    "time": "03/03/2026"
  },
  {
    "title": "الأكاديمية المالية تعلن برنامج نخبة الخريجين في إدارة الأصول بالرياض ولندن",
    "link": "https://www.ewdifh.com/jobs/84641",
    "company": "الأكاديمية المالية",
    "time": "منذ 13 ساعة"
  },
  {
    "title": "مجموعة باسمح تعلن وظائف مبيعات وتخصصات إدارية في عدة مدن بالمملكة",
    "link": "https://www.ewdifh.com/jobs/84642",
    "company": "شركة باسمح التجارية",
    "time": "منذ 9 ساعات"
  },
  {
    "title": "جامعة الأمير سطام تعلن وظائف أكاديمية (نقل خدمات) للرجال والنساء",
    "link": "https://www.ewdifh.com/jobs/84637",
    "company": "جامعة الأمير سطام",
    "time": "منذ 23 ساعة"
  },
  {
    "title": "هيئة الزكاة والضريبة والجمارك تعلن وظائف إدارية وتقنية وهندسية بالرياض",
    "link": "https://www.ewdifh.com/jobs/84619",
    "company": "هيئة الزكاة والضريبة والجمارك",
    "time": "منذ 5 أيام"
  },
  {
    "title": "موظف استقبال تأجير سيارات",
    "link": "https://www.wadhefa.com/details/job/89033/",
    "company": "الرياض - منطقة الرياض",
    "time": "اليوم"
  }
]