[
  {
    "title": "المؤسسة العامة للتدريب التقني والمهني تعلن برنامج مكّن المرحلة الثالثة",
    "link": "https://www.wadhefa.com/news/20380/",
    "company": "اعلان توظيف",
    "time": "02/04/2026"
  },
  {
    "title": "الهيئة العامة للموانئ تعلن عن طرح وظائف تقنية وهندسية للعمل في الرياض",
    "link": "https://www.wadhefa.com/news/20381/",
    "company": "موقع الهيئة",
    "time": "02/04/2026"
  },
  {
    "title": "جامعة طيبة تعلن فتح باب القبول في برامج الدراسات العليا للعام 1448هـ (المجانية)",
    "link": "https://www.ewdifh.com/jobs/84799",
    "company": "جامعة طيبة",
    "time": "منذ يومين"
  },
  {
    "title": "الهيئة السعودية للملكية الفكرية تعلن وظائف هندسية وإدارية وفنية بالرياض",
    "link": "https://www.ewdifh.com/jobs/84816",
    "company": "الهيئة السعودية للملكية الفكرية",
    "time": "منذ 18 ساعة"
  },
  {
    "title": "محاسب عام",
    "link": "https://www.wadhefa.com/details/job/89181/",
    "company": "الرياض",
    "time": "02/04/2026"
  },
  {
    "title": "الخدمات الطبية بوزارة الداخلية تعلن ابتعاث خارجي لدراسة بكالوريوس التمريض",
    "link": "https://www.ewdifh.com/jobs/84798",
    "company": "وزارة الداخلية",
    "time": "منذ يومين"
  },
  {
    "title": "البنك السعودي الأول ساب يعلن وظائف إدارية وتقنية لحملة البكالوريوس بالرياض",
    "link": "https://www.ewdifh.com/jobs/84789",
    "company": "البنك السعودي الأول",
    "time": "منذ 3 أيام"
  },
  {
    "title": "اخصائي تسويق",
    "link": "https://www.wadhefa.com/details/job/89185/",
    "company": "جدة",
    "time": "02/04/2026"
  },
  {
    "title": "اخصائي تسويق",
    "link": "https://www.wadhefa.com/details/job/89119/",
    "company": "الرياض - منطقة الرياض",
    "time": "اليوم"
  },
  {
    "title": "شركة سابك تعلن وظائف هندسية وفنية لحملة الدبلوم والبكالوريوس بالجبيل",
    "link": "https://www.ewdifh.com/jobs/84796",
    "company": "شركة سابك",
    "time": "منذ 3 أيام"
  },
  {
    "title": "معلم تربية اسلامية",
    "link": "https://www.wadhefa.com/details/job/89184/",
    "company": "الدمام",
    "time": "02/04/2026"
  },
  {
    "title": "موظف استقبال تأجير سيارات",
    "link": "https://www.wadhefa.com/details/job/89033/",
    "company": "الرياض - منطقة الرياض",
    "time": "اليوم"
  },
  {
    "title": "شركة آيتونمي تعلن برنامج الابتعاث المبتدئ بالتوظيف في ألمانيا (مسار واعد)",
    "link": "https://www.ewdifh.com/jobs/84814",
    "company": "برنامج خادم الحرمين الشريفين للابتعاث",
    "time": "منذ 20 ساعة"
  },
  {
    "title": "مجموعة الراشد تعلن وظائف إدارية وهندسية وفنية بعدة مدن بالمملكة",
    "link": "https://www.ewdifh.com/jobs/84793",
    "company": "مجموعة شركات راشد الراشد وأولاده",
    "time": "منذ 3 أيام"
  },
  {
    "title": "معلم تربية بدنية",
    "link": "https://www.wadhefa.com/details/job/89183/",
    "company": "الدمام",
    "time": "02/04/2026"
  },
  {
    "title": "كاتب تأجير سيارات",
    "link": "https://www.wadhefa.com/details/job/89168/",
    "company": "تبوك - منطقة تبوك",
    "time": "اليوم"
  },
  {
    "title": "محاسب",
    "link": "https://www.wadhefa.com/details/job/89179/",
    "company": "الرياض",
    "time": "01/04/2026"
  },
  {
    "title": "موظف مركز اتصال",
    "link": "https://www.wadhefa.com/details/job/89144/",
    "company": "الرياض - منطقة الرياض",
    "time": "اليوم"
  },
  {
    "title": "المؤسسة العامة للتدريب التقني تعلن بدء التسجيل في برنامج (مكّن) للدبلوم المجاني",
    "link": "https://www.ewdifh.com/jobs/84813",
    "company": "المؤسسة العامة للتدريب التقني والمهني",
    "time": "منذ يوم"
  },
  {
    "title": "شركة المراعي تعلن عن توفر وظائف شاغرة (ثانوية فأعلى) في عدة مدن بالمملكة",
    "link": "https://www.ewdifh.com/jobs/84811",
    "company": "شركة المراعي",
    "time": "منذ يوم"
  },
  {
    "title": "شركة حسن جميل للسيارات تعلن وظائف مبيعات بالدمام براتب يصل 7,500 ريال",
    "link": "https://www.ewdifh.com/jobs/84810",
    "company": "شركة حسن جميل للسيارات",
    "time": "منذ يوم"
  },
  {
    "title": "وزارة الطاقة توفر وظيفة مساعد إداري لحملة الثانوية العامة بمدينة الرياض",
    "link": "https://www.ewdifh.com/jobs/84804",
    "company": "وزارة الطاقة",
    "time": "منذ يوم"
  },
  {
    "title": "مطور اعمال",
    "link": "https://www.wadhefa.com/details/job/89186/",
    "company": "الرياض",
    "time": "02/04/2026"
  },
  {
    "title": "شركة آيوا تعلن وظائف شاغرة بمسمى مستشار مبيعات في مختلف مدن المملكة",
    "link": "https://www.ewdifh.com/jobs/84808",
    "company": "متاجر ايوا (Eyewa)",
    "time": "منذ يوم"
  },
  {
    "title": "جامعة الرياض للفنون تعلن انطلاقها وفتح باب القبول في عدة كليات بمدينة الرياض",
    "link": "https://www.ewdifh.com/jobs/84795",
    "company": "جامعة الرياض للفنون",
    "time": "منذ 3 أيام"
  },
  {
    "title": "اخصائي موارد بشرية",
    "link": "https://www.wadhefa.com/details/job/89145/",
    "company": "الرياض - منطقة الرياض",
    "time": "اليوم"
  },
  {
    "title": "مكتبة الملك فهد العامة تعلن 7 دورات تدريبية مجانية (عن بُعد) في عدة مجالات",
    "link": "https://www.ewdifh.com/jobs/84809",
    "company": "مكتبة الملك فهد العامة بجدة",
    "time": "منذ يوم"
  },
  {
    "title": "هيئة الزكاة والضريبة والجمارك تعلن عن طرح 6 وظائف إدارية وقانونية شاغرة",
    "link": "https://www.wadhefa.com/news/20383/",
    "company": "موقع الهيئة",
    "time": "02/04/2026"
  },
  {
    "title": "شركة التنفيذي تعلن وظائف تقنية وإدارية شاغرة لحملة البكالوريوس بالرياض",
    "link": "https://www.ewdifh.com/jobs/84807",
    "company": "شركة التنفيذي",
    "time": "منذ يوم"
  },
  {
    "title": "شركة أتمال الراجحي للخدمات سابقا تعلن وظائف إدارية وتقنية بمدينة الرياض",
    "link": "https://www.ewdifh.com/jobs/84801",
    "company": "شركة أتمال",
    "time": "منذ يومين"
  },
  {
    "title": "مستشفى الملك خالد التخصصي للعيون يعلن وظائف طبية وإدارية لحملة الدبلوم فأعلى",
    "link": "https://www.ewdifh.com/jobs/84797",
    "company": "مستشفى الملك خالد التخصصي للعيون",
    "time": "منذ يومين"
  },
  {
    "title": "البنك الأهلي يعلن وظائف مدير علاقة المنشآت الصغيرة والمتوسطة بمناطق المملكة",
    "link": "https://www.ewdifh.com/jobs/84792",
    "company": "البنك الأهلي السعودي",
    "time": "منذ 3 أيام"
  },
  {
    "title": "شركة نايس ون تعلن طرح 35 وظيفة شاغرة للجنسين بعدة مدن بالمملكة",
    "link": "https://www.ewdifh.com/jobs/84790",
    "company": "شركة نايس ون",
    "time": "منذ 3 أيام"
  },
  {
    "title": "كاتب تأجير سيارات",
    "link": "https://www.wadhefa.com/details/job/89159/",
    "company": "الرياض - منطقة الرياض",
    "time": "اليوم"
  },
  {
    "title": "مدير فروع مطاعم",
    "link": "https://www.wadhefa.com/details/job/89182/",
    "company": "جدة",
    "time": "02/04/2026"
  },
  {
    "title": "صندوق هدف يعلن 8 دورات تدريبية مجانية (عن بُعد) لتعليم اللغة الإنجليزية",
    "link": "https://www.ewdifh.com/jobs/84800",
    "company": "صندوق تنمية الموارد البشرية (هدف)",
    "time": "منذ يومين"
  },
  {
    "title": "Sales Executive",
    "link": "https://www.wadhefa.com/details/job/89113/",
    "company": "الرياض - منطقة الرياض",
    "time": "اليوم"
  },
  {
    "title": "بائع",
    "link": "https://www.wadhefa.com/details/job/89055/",
    "company": "الخبر - المنطقة الشرقية",
    "time": "اليوم"
  },
  {
    "title": "الهيئة السعودية للملكية الفكرية تعلن وظائف شاغرة في عدد من التخصصات",
    "link": "https://www.wadhefa.com/news/20382/",
    "company": "اعلان توظيف",
    "time": "02/04/2026"
  },
  {
    "title": "محاسب",
    "link": "https://www.wadhefa.com/details/job/89187/",
    "company": "ينبع",
    "time": "03/04/2026"
  }
]